[
  {
    "Name": "nofar_06",
    "Part": "https://s3.amazonaws.com/factoryfour-dist-static/pq/typeF_v44.ipt",
    "Parameters": {
        "RightNoseAngle": 80.51,
        "LeftNoseAngle": 79.45,
        "RightNoseWidth": 11.382351561532447,
        "LeftNoseWidth": 9.749486219285794,
        "PupilDist": 59.77707356102161,
        "SupMed_h": 11.167576789297062,
        "SupLat_h": 17.123617743588827,
        "InfLat_h": 18.61262798216177,
        "InfMed_h": 18.147312282607725,
        "SupMed_w": 6.199999999999994,
        "SupLat_w": 67.52860920122302,
        "InfLat_w": 53.01075937513684,
        "InfMed_w": 15.040998291526835,
        "SupMedRounding": 6.51441979375662,
        "SupLatRounding": 5.583788394648532,
        "InfLatRounding": 6.886672353399855,
        "InfMedRounding": 6.51441979375662,
        "SupMedThickness": 3.6,
        "SupLatThickness": 5.6,
        "InfLatThickness": 2.3,
        "InfMedThickness": 2,
        "BridgeHeight": 9.492440270902502,
        "BridgeThickness": 5.5,
        "TempleHeight": 13.361770474079382,
        "HingeThickness": 6.5,
        "RightTemple_yz": 1.3319419670223687,
        "LeftTemple_yz": 0.5116872560155662,
        "RightTemple_xz": -0.13928179867707513,
        "LeftTemple_xz": 0.3520040404873157,
        "Temple_length": 56.31700352580286,
        "FrameID": "NO06"
      }
  },

  {
    "Name": "nofar_08",
    "Part": "https://s3.amazonaws.com/factoryfour-dist-static/pq/typeF_v44.ipt",
    "Parameters": {
        "RightNoseAngle": 80.51,
        "LeftNoseAngle": 79.45,
        "RightNoseWidth": 11.382351561532447,
        "LeftNoseWidth": 9.749486219285794,
        "PupilDist": 59.77707356102161,
        "SupMed_h": 12.371231899624021,
        "SupLat_h": 14.956265430888742,
        "InfLat_h": 23.357624407499085,
        "InfMed_h": 23.63459228584888,
        "SupMed_w": 4.899999999999999,
        "SupLat_w": 62.87860920122303,
        "InfLat_w": 51.98453931946456,
        "InfMed_w": 19.117684421955964,
        "SupMedRounding": 9.232262611659719,
        "SupLatRounding": 7.385810089327774,
        "InfLatRounding": 11.078715133991661,
        "InfMedRounding": 11.078715133991661,
        "SupMedThickness": 4,
        "SupLatThickness": 5.4,
        "InfLatThickness": 2.6,
        "InfMedThickness": 2,
        "BridgeHeight": 12.37123189962402,
        "BridgeThickness": 7,
        "TempleHeight": 10.53303916972277,
        "HingeThickness": 7,
        "RightTemple_yz": 3.1456678536371214,
        "LeftTemple_yz": 2.378274819886144,
        "RightTemple_xz": -2.8056895579317143,
        "LeftTemple_xz": 3.05745700792113,
        "Temple_length": 58.52487846332322,
        "FrameID": "NO08"
      }
  }
]
